pygaul/__init__.py
pygaul/data/gaul_continent.json
pygaul/data/gaul_database.parquet
pygaul-0.3.4.dist-info/LICENSE
pygaul-0.3.4.dist-info/METADATA
pygaul-0.3.4.dist-info/WHEEL
pygaul-0.3.4.dist-info/top_level.txt
pygaul-0.3.4.dist-info/RECORD
