Metadata-Version: 2.1
Name: pygaul
Version: 0.3.4
Summary: Easy access to administrative boundary defined by FAO GAUL from a Python script.
Author-email: Pierrick Rambaud <pierrick.rambaud49@gmail.com>
License: MIT
Project-URL: Homepage, https://github.com/12rambau/pygaul
Keywords: skeleton,Python
Classifier: Development Status :: 3 - Alpha
Classifier: Intended Audience :: Developers
Classifier: License :: OSI Approved :: MIT License
Classifier: Programming Language :: Python :: 3.7
Classifier: Programming Language :: Python :: 3.8
Classifier: Programming Language :: Python :: 3.9
Classifier: Programming Language :: Python :: 3.10
Classifier: Programming Language :: Python :: 3.11
Requires-Python: >=3.7
License-File: LICENSE
Requires-Dist: deprecated >=1.2.14
Requires-Dist: pandas
Requires-Dist: earthengine-api
Requires-Dist: pyarrow
Provides-Extra: dev
Requires-Dist: pre-commit ; extra == 'dev'
Requires-Dist: commitizen ; extra == 'dev'
Requires-Dist: nox ; extra == 'dev'
Provides-Extra: doc
Requires-Dist: sphinx <7,>=6.2.1 ; extra == 'doc'
Requires-Dist: pydata-sphinx-theme ; extra == 'doc'
Requires-Dist: sphinx-copybutton ; extra == 'doc'
Requires-Dist: sphinx-design ; extra == 'doc'
Requires-Dist: sphinx-icon ; extra == 'doc'
Requires-Dist: sphinx-autoapi ; extra == 'doc'
Requires-Dist: geemap ; extra == 'doc'
Requires-Dist: jupyter-sphinx !=0.4.0 ; extra == 'doc'
Requires-Dist: httplib2 ; extra == 'doc'
Requires-Dist: ipykernel ; extra == 'doc'
Provides-Extra: test
Requires-Dist: pytest ; extra == 'test'
Requires-Dist: pytest-sugar ; extra == 'test'
Requires-Dist: pytest-cov ; extra == 'test'
Requires-Dist: pytest-deadfixtures ; extra == 'test'
Requires-Dist: httplib2 ; extra == 'test'
Requires-Dist: pytest-regressions >=2.4.3 ; extra == 'test'
Requires-Dist: pytest-gee ; extra == 'test'
